laRVa2_DC/mult_signo_ori.v
//////////////////////////////////////////////////////////////////////////////////////
//////////////////////////////////////////////////////////////////////////////////////
////  			  RV32IM extension: Multiply & Divide instructions
////						arithmethic modules
////						Multiplier module extracted from laRVa.v
//////////////////////////////////////////////////////////////////////////////////////
//////////////////////////////////////////////////////////////////////////////////////

///////////////////////////////////////////////
///////////////////////////////////////////////
// 	Multiplier: simple shift-reg, 1 cycle/bit
///////////////////////////////////////////////
///////////////////////////////////////////////

module multiplier (
	input  clk,
	input  reset,		// async. reset
	input  [31:0]a,		// Multiplier (rs2)
	input  [31:0]b,		// Multiplicand (rs1)
	input  ua,			// unsigned multiplier
	input  ub,			// unsigned multiplicand
	input  hm,			// return high word (bits 63:32)
	input  load,		// load strobe
	output busy,		// doing processing while 1
	output [31:0]out	// output result
);

// last multiplication data
reg [31:0]oa;
reg [31:0]ob;
reg oua;
reg oub;
always @(posedge clk or posedge reset) if (reset) {oua,oa}<=0; else if (load) {oua,oa}<={ua,a};
always @(posedge clk or posedge reset) if (reset) {oub,ob}<=0; else if (load) {oub,ob}<={ub,b};

// internal load if needed
wire iload = load & ( ({oa,ob}!={a,b}) | (hm & ({oua,oub}!={ua,ub})));

// make multiplicand positive
wire sma = (~ua)&a[31];	// signed multiplier
wire [31:0]ma = (sma ? (~a) : a) +sma;	// change sign if needed
wire [31:0]mb = (sma ? (~b) : b) +sma;	// change sign if needed

// shift operands	
reg [31:0]sha=0;
always @(posedge clk or posedge reset) 
	if (reset) sha<=0; else sha<= iload ? ma : {1'b0,sha[31:1]};
assign busy=iload |(|sha);

reg [63:0]shb;
always @(posedge clk) shb<= iload ? { ub ? 32'b0 : {32{mb[31]}},mb} : 
							{shb[62:0],1'b0};

// accumulator
reg [63:0]acc;
always @(posedge clk or posedge reset)
	if (reset) acc<=0;
	else if (iload | sha[0]) acc <= iload ? 0 : acc + shb;

assign out= hm ? acc[63:32] : acc[31:0];
endmodule

laRVa2_DC/multiplier_4bit_tb.v
`timescale 1ns/1ps
`include "mult_signo_ori.v"
module multiplier_4bit_tb;

    // Señales del DUT (Device Under Test)
    reg clk;
    reg reset;
    reg [31:0] a;
    reg [31:0] b;
    reg ua;
    reg ub;
    reg hm;
    reg load;
    wire busy;
    wire [31:0] out;
    
    // Variables auxiliares para verificación
    reg [63:0] resultado_esperado;
    reg [63:0] resultado_capturado;
    integer errores;
    integer pruebas;
    
    // Instanciar el DUT
//   multiplier_4bit_sequential DUT (
	multiplier DUT(		// Jesus Arias implementation
        .clk(clk),
        .reset(reset),
        .a(a),
        .b(b),
        .ua(ua),
        .ub(ub),
        .hm(hm),
        .load(load),
        .busy(busy),
        .out(out)
    );
    
    // Generador de reloj
    initial begin
        clk = 0;
        forever #5 clk = ~clk;  // Periodo de 10ns
    end
    
    // Tareas auxiliares
    
    // Tarea para calcular resultado esperado
    task calcular_esperado;
        input [31:0] op_a;
        input [31:0] op_b;
        input unsigned_a;
        input unsigned_b;
        output [63:0] esperado;
        begin
            if (unsigned_a && unsigned_b) begin
                // Ambos sin signo
                esperado = op_a * op_b;
            end else if (!unsigned_a && !unsigned_b) begin
                // Ambos con signo
                esperado = {{32{op_a[31]}},op_a} * {{32{op_b[31]}},op_b};
 //               esperado = $signed(op_a) * $signed(op_b);
            end else if (!unsigned_a && unsigned_b) begin
                // a con signo, b sin signo
                esperado = {{32{op_a[31]}},op_a} * op_b;
            end else begin
                // a sin signo, b con signo
                esperado = op_a * {{32{op_b[31]}},op_b};
            end
        end
    endtask
    
    // Tarea para ejecutar una multiplicación
    task ejecutar_multiplicacion;
        input [31:0] op_a;
        input [31:0] op_b;
        input unsigned_a;
        input unsigned_b;
        input obtener_high;
        input [255:0] descripcion;
        begin
            $display("\n=== Prueba %0d: %0s ===", pruebas + 1, descripcion);
            $display("A = %d (0x%08h), B = %d (0x%08h)", 
                     unsigned_a ? op_a : $signed(op_a), op_a,
                     unsigned_b ? op_b : $signed(op_b), op_b);
            $display("UA = %b, UB = %b, HM = %b", unsigned_a, unsigned_b, obtener_high);
            
            // Configurar operación
            a = op_a;
            b = op_b;
            ua = unsigned_a;
            ub = unsigned_b;
            hm = obtener_high;
            
            // Calcular resultado esperado
            calcular_esperado(op_a, op_b, unsigned_a, unsigned_b, resultado_esperado);
            
            // Iniciar multiplicación
            #2 load = 1;
            #10 load = 0;

            // Esperar a que termine
            wait (!busy);
			#2;	// aparece el resultado más tarde

            // Capturar resultado de palabra baja
            if (!obtener_high) begin
                resultado_capturado = out;
                $display("Resultado (low): 0x%08h", out);
                $display("Esperado  (low): 0x%08h", resultado_esperado[31:0]);
                
                if (out !== resultado_esperado[31:0]) begin
                    $display("ERROR: Resultado incorrecto en palabra baja!");
                    errores = errores + 1;
                end else begin
                    $display("CORRECTO: Palabra baja");
                end
            end
            
            // Para verificar palabra alta, ejecutar de nuevo con hm=1
            if (obtener_high) begin
                // Siempre verificar palabra alta

//               while (busy);
                resultado_capturado = out;             
                $display("Resultado (high): 0x%08h", out);
                $display("Esperado  (high): 0x%08h", resultado_esperado[63:32]);
                
                if (out !== resultado_esperado[63:32]) begin
                    $display("ERROR: Resultado incorrecto en palabra alta!");
                    errores = errores + 1;
                end else begin
                    $display("CORRECTO: Palabra alta");
                end
            end
            
            pruebas = pruebas + 1;
            @(posedge clk);
        end
    endtask
    
    // Programa principal de pruebas
    initial begin
        // Inicialización
        $dumpfile("multiplier_4bit_tb.vcd");
        $dumpvars(0, multiplier_4bit_tb);
        
        errores = 0;
        pruebas = 0;
        reset = 1;
        a = 0;
        b = 0;
        ua = 0;
        ub = 0;
        hm = 0;
        load = 0;
        
        // Reset del sistema
        #20 reset = 0;
        @(posedge clk);
        
        $display("\n========================================");
        $display("  INICIO DE PRUEBAS DEL MULTIPLICADOR");
        $display("========================================");
        // PRUEBA 1: Números pequeños positivos (parte baja)
        ejecutar_multiplicacion(32'd5, 32'd7, 1, 1, 0, "Num bajos ++ (5 x 7) low");
        // PRUEBA 2: Números pequeños positivos (parte alta)
        // ejecutar_multiplicacion(32'd5, 32'd7, 1, 1, 1, "Num bajos ++ (5 x 7) high");
        // PRUEBA 3: Números pequeños con diferente signo (parte baja)
        ejecutar_multiplicacion(32'd5, -32'd7, 1, 0, 0, "Num bajos +- (5 x -7) low");
        // PRUEBA 4: Números pequeños con diferente signo (parte alta)
        // ejecutar_multiplicacion(32'd5, -32'd7, 1, 0, 1, "Num bajos +- (5 x -7) high");
        // PRUEBA 5: Números pequeños con diferente signo (parte baja)
        // ejecutar_multiplicacion(-32'd5, 32'd7, 0, 0, 0, "Num bajos -+ (-5 x 7) low");
        // PRUEBA 6: Números pequeños con diferente signo (parte alta)
        // ejecutar_multiplicacion(-32'd5, 32'd7, 0, 0, 1, "Num bajos -+ (-5 x 7) high");
        // PRUEBA 7: Números pequeños ambos negativos
        // ejecutar_multiplicacion(-32'd5, -32'd7, 0, 0, 0, "Num bajos -- (-5 x -7) low");
        // PRUEBA 8: Números pequeños ambos negativos
        ejecutar_multiplicacion(-32'd5, -32'd7, 0, 0, 1, "Num bajos -- (-5 x -7) high");
        
        // PRUEBA 9: Multiplicación por cero
        // ejecutar_multiplicacion(32'd12345, 32'd0, 1, 1, 0, "Multando = 0 low");
        // PRUEBA 10: Multiplicación por cero
        // ejecutar_multiplicacion(32'd12345, 32'd0, 1, 1, 1, "Multando = 0 high");
        // PRUEBA 11: Multiplicación por cero
        // ejecutar_multiplicacion(32'd0, 32'd12345, 1, 1, 0, "Mulor = 0 low");
        // PRUEBA 12: Multiplicación por cero
        // ejecutar_multiplicacion(32'd0, 32'd12345, 1, 1, 1, "Mulor = 0 high");
        
        // PRUEBA 13: Multiplicación por uno
        // ejecutar_multiplicacion(32'd12345, 32'd1, 1, 1, 0, "Multiplicacion por 1 low");
        // PRUEBA 14: Multiplicación por uno
        // ejecutar_multiplicacion(32'd12345, 32'd1, 1, 1, 1, "Multiplicacion por 1 high");
        // PRUEBA 15: Multiplicación por -1
        // ejecutar_multiplicacion(32'd12345, -32'd1, 1, 0, 0, "Multiplicacion por -1 low");
        // PRUEBA 16: Multiplicación por -1
        // ejecutar_multiplicacion(32'd12345, -32'd1, 1, 0, 1, "Multiplicacion por -1 high");
        
        // PRUEBA 17: Números muy grandes sin signo
        // ejecutar_multiplicacion(32'hFFFFFFFF, 32'hFFFFFFFF, 1, 1, 0, 
        //                       "altos unsigned (2^32-1 x 2^32-1) low");
        // PRUEBA 18: Números muy grandes sin signo
        // ejecutar_multiplicacion(32'hFFFFFFFF, 32'hFFFFFFFF, 1, 1, 1, 
        //                       "altos unsigned (2^32-1 x 2^32-1) high");
        
        // PRUEBA 19: Números grandes con signo positivo
        // ejecutar_multiplicacion(32'h7FFFFFFF, 32'h7FFFFFFF, 0, 0, 0, 
        //                       "altos signed + (2^31-1 x 2^31-1) low");
        // PRUEBA 20: Números grandes con signo positivo
        // ejecutar_multiplicacion(32'h7FFFFFFF, 32'h7FFFFFFF, 0, 0, 1, 
        //                       "altos signed + (2^31-1 x 2^31-1) high");
        
        // PRUEBA 21: Números grandes con diferente signo
        // ejecutar_multiplicacion(32'h7FFFFFFF, 32'h80000000, 0, 0, 0, 
        //                       "grande signo + x grande signo low");
        // PRUEBA 22: Números grandes con diferente signo
        // ejecutar_multiplicacion(32'h7FFFFFFF, 32'h80000000, 0, 0, 1, 
        //                       "grande signo + x grande signo high");
        
        // PRUEBA 23: Casos de overflow intermedio
        // ejecutar_multiplicacion(32'h10000, 32'h10000, 1, 1, 0, 
        //                       "65536 x 65536 (overflow a palabra alta) low");
        // PRUEBA 24: Casos de overflow intermedio
        // ejecutar_multiplicacion(32'h10000, 32'h10000, 1, 1, 1, 
        //                       "65536 x 65536 (overflow a palabra alta) high");
        
        // PRUEBA 25: Patrones de bits especiales
        // ejecutar_multiplicacion(32'h55555555, 32'hAAAAAAAA, 1, 1, 0, 
        //                       "signed (0x5555... x 0xAAAA...) low");
        // PRUEBA 26: Patrones de bits especiales
        // ejecutar_multiplicacion(32'h55555555, 32'hAAAAAAAA, 1, 1, 1, 
        //                       "signed (0x5555... x 0xAAAA...) high");
        
        // PRUEBA 27: Números con muchos ceros en nibbles
        // ejecutar_multiplicacion(32'h00FF00FF, 32'h0F0F0F0F, 1, 1, 0, 
        //                       "Numeros con nibbles cero low");
        // PRUEBA 28: Números con muchos ceros en nibbles
        // ejecutar_multiplicacion(32'h00FF00FF, 32'h0F0F0F0F, 1, 1, 1, 
        //                       "Numeros con nibbles cero high");
        
        // PRUEBA 29: Potencias de 2
        // ejecutar_multiplicacion(32'd1024, 32'd2048, 1, 1, 0, 
        //                       "Potencias de 2 (1024 x 2048)low");
        // PRUEBA 30: Potencias de 2
        // ejecutar_multiplicacion(32'd1024, 32'd2048, 1, 1, 1, 
        //                       "Potencias de 2 (1024 x 2048)high");
        
        // PRUEBA 31: Números primos grandes
        // ejecutar_multiplicacion(32'd65537, 32'd65521, 1, 1, 0, 
        //                       "Numeros primos grandes low");
        // PRUEBA 32: Números primos grandes
        // ejecutar_multiplicacion(32'd65537, 32'd65521, 1, 1, 1, 
        //                       "Numeros primos grandes high");

        // PRUEBA 33: Maximo sin signo x -1       
        // ejecutar_multiplicacion(32'hFFFFFFFF, -32'd1, 1, 0, 0, 
        //                       "Maximo sin signo x -1 low");
        // PRUEBA 34: Maximo sin signo x -1       
        // ejecutar_multiplicacion(32'hFFFFFFFF, -32'd1, 1, 0, 1, 
        //                       "Maximo sin signo x -1 high");
        
        // PRUEBA 35: Números aleatorios
        // ejecutar_multiplicacion(32'd123456789, 32'd987654321, 1, 1, 0, 
        //                       "Numeros aleatorios grandes low");
        // PRUEBA 36: Números aleatorios
        // ejecutar_multiplicacion(32'd123456789, 32'd987654321, 1, 1, 1, 
        //                       "Numeros aleatorios grandes high");
        
        // PRUEBA 37: Caso especial -1 x -1
        // ejecutar_multiplicacion(32'hFFFFFFFF, 32'hFFFFFFFF, 0, 0, 0, 
        //                       "(-1) x (-1) con signo, low");
        // PRUEBA 38: Caso especial -1 x -1
        // ejecutar_multiplicacion(32'hFFFFFFFF, 32'hFFFFFFFF, 0, 0, 1, 
        //                       "(-1) x (-1) con signo, high");

        // PRUEBA 39: Número maximo con signo negativo en A
        // ejecutar_multiplicacion(32'h80000000, 32'hFFFFFFFF, 0, 0, 0, 
        //                       "max signed - (-2^31-1 x -1) low");
        // PRUEBA 40: Número maximo con signo negativo en A
        // ejecutar_multiplicacion(32'h80000000, 32'hFFFFFFFF, 0, 0, 1, 
        //                       "max signed - (-2^31-1 x -1) high");
        
        // PRUEBA 41: Número maximo con signo negativo en B
        // ejecutar_multiplicacion(32'hFFFFFFFF, 32'h80000000, 0, 0, 0, 
        //                       "max signed - (-1 x -2^31-1) low");
        // PRUEBA 42: Número maximo con signo negativo en B
        // ejecutar_multiplicacion(32'hFFFFFFFF, 32'h80000000, 0, 0, 1, 
        //                       "max signed - (-1 x -2^31-1) high");
        
        // PRUEBA 43: Números max con signo negativo
        // ejecutar_multiplicacion(32'h80000000, 32'h80000000, 0, 0, 0, 
        //                       "max signo - (-2^31 x -2^31) low");
        // PRUEBA 44: Números max con signo negativo
        // ejecutar_multiplicacion(32'h80000000, 32'h80000000, 0, 0, 1, 
        //                       "max signo - (-2^31 x -2^31) high");
        

        
        // Resumen final
        $display("\n========================================");
        $display("  RESUMEN DE PRUEBAS");
        $display("========================================");
        $display("Total de pruebas ejecutadas: %0d", pruebas);
        $display("Errores encontrados: %0d", errores);
        if (errores == 0) begin
            $display("¡TODAS LAS PRUEBAS PASARON EXITOSAMENTE!");
        end else begin
            $display("ATENCION: Se encontraron errores en las pruebas");
        end
        $display("========================================\n");
        
        // Esperar un poco antes de terminar
        #100;
        $finish;
    end
    
/*    // Monitor para debugging
    initial begin
        $monitor("Tiempo=%0t, Estado: reset=%b, load=%b, busy=%b, ciclo_actual=%d", 
                 $time, reset, load, busy, DUT.ciclo_count);
    end
*/

endmodule

laRVa2_DC/multiplier_4bit_tb.vcd
$date
	Wed Nov 19 14:28:24 2025
$end
$version
	Icarus Verilog
$end
$timescale
	1ps
$end
$scope module multiplier_4bit_tb $end
$var wire 1 ! busy $end
$var wire 32 " out [31:0] $end
$var reg 32 # a [31:0] $end
$var reg 32 $ b [31:0] $end
$var reg 1 % clk $end
$var integer 32 & errores [31:0] $end
$var reg 1 ' hm $end
$var reg 1 ( load $end
$var integer 32 ) pruebas [31:0] $end
$var reg 1 * reset $end
$var reg 64 + resultado_capturado [63:0] $end
$var reg 64 , resultado_esperado [63:0] $end
$var reg 1 - ua $end
$var reg 1 . ub $end
$scope module DUT $end
$var wire 32 / a [31:0] $end
$var wire 32 0 b [31:0] $end
$var wire 1 ! busy $end
$var wire 1 1 clk $end
$var wire 1 2 hm $end
$var wire 1 3 iload $end
$var wire 1 4 load $end
$var wire 32 5 ma [31:0] $end
$var wire 32 6 mb [31:0] $end
$var wire 32 7 out [31:0] $end
$var wire 1 8 reset $end
$var wire 1 9 sma $end
$var wire 1 : ua $end
$var wire 1 ; ub $end
$var reg 64 < acc [63:0] $end
$var reg 32 = oa [31:0] $end
$var reg 32 > ob [31:0] $end
$var reg 1 ? oua $end
$var reg 1 @ oub $end
$var reg 32 A sha [31:0] $end
$var reg 64 B shb [63:0] $end
$upscope $end
$scope task calcular_esperado $end
$var reg 64 C esperado [63:0] $end
$var reg 32 D op_a [31:0] $end
$var reg 32 E op_b [31:0] $end
$var reg 1 F unsigned_a $end
$var reg 1 G unsigned_b $end
$upscope $end
$scope task ejecutar_multiplicacion $end
$var reg 256 H descripcion [255:0] $end
$var reg 1 I obtener_high $end
$var reg 32 J op_a [31:0] $end
$var reg 32 K op_b [31:0] $end
$var reg 1 L unsigned_a $end
$var reg 1 M unsigned_b $end
$upscope $end
$upscope $end
$enddefinitions $end
#0
$dumpvars
xM
xL
bx K
bx J
xI
bx H
xG
xF
bx E
bx D
bx C
bx B
b0 A
0@
0?
b0 >
b0 =
b0 <
0;
0:
09
18
b0 7
b0 6
b0 5
04
03
02
01
b0 0
b0 /
0.
0-
bx ,
bx +
1*
b0 )
0(
0'
b0 &
0%
b0 $
b0 #
b0 "
0!
$end
#5000
bx0 B
1%
11
#10000
0%
01
#15000
bx00 B
1%
11
#20000
0%
01
0*
08
#25000
bx000 B
b111 6
b101 5
b100011 ,
b100011 C
1G
1F
b111 E
b101 D
1.
1;
1-
1:
b111 $
b111 0
b101 #
b101 /
b10011100111010101101101001000000110001001100001011010100110111101110011001000000010101100101011001000000010100000110101001000000111100000100000001101110010100100100000011011000110111101110111 H
0I
1M
1L
b111 K
b101 J
1%
11
#27000
1!
13
1(
14
#30000
0%
01
#35000
03
1?
b101 =
1@
b111 >
b101 A
b111 B
1%
11
#37000
0(
04
#40000
0%
01
#45000
b111 "
b111 7
b111 <
b10 A
b1110 B
1%
11
#50000
0%
01
#55000
b1 A
b11100 B
1%
11
#60000
0%
01
#65000
b100011 "
b100011 7
0!
b100011 <
b0 A
b111000 B
1%
11
#67000
b1 )
b100011 +
#70000
0%
01
#75000
b1110000 B
b11111111111111111111111111111001 6
b1111111111111111111111111111111111111111111111111111111111011101 ,
b1111111111111111111111111111111111111111111111111111111111011101 C
0G
b11111111111111111111111111111001 E
0.
0;
b11111111111111111111111111111001 $
b11111111111111111111111111111001 0
b1001110011101010110110100100000011000100110000101101010011011110111001100100000001010110010110100100000001010000011010100100000011110000010000000101101001101110010100100100000011011000110111101110111 H
0M
b11111111111111111111111111111001 K
1%
11
#77000
1!
13
1(
14
#80000
0%
01
#85000
b0 "
b0 7
03
b0 <
b101 A
0@
b11111111111111111111111111111001 >
b1111111111111111111111111111111111111111111111111111111111111001 B
1%
11
#87000
0(
04
#90000
0%
01
#95000
b11111111111111111111111111111001 "
b11111111111111111111111111111001 7
b10 A
b1111111111111111111111111111111111111111111111111111111111111001 <
b1111111111111111111111111111111111111111111111111111111111110010 B
1%
11
#100000
0%
01
#105000
b1 A
b1111111111111111111111111111111111111111111111111111111111100100 B
1%
11
#110000
0%
01
#115000
b11111111111111111111111111011101 "
b11111111111111111111111111011101 7
0!
b0 A
b1111111111111111111111111111111111111111111111111111111111011101 <
b1111111111111111111111111111111111111111111111111111111111001000 B
1%
11
#117000
b10 )
b11111111111111111111111111011101 +
#120000
0%
01
#125000
b1111111111111111111111111111111111111111111111111111111110010000 B
19
b111 6
b11111111111111111111111111111111 "
b11111111111111111111111111111111 7
b101 5
b100011 ,
b100011 C
0F
b11111111111111111111111111111011 D
1'
12
0-
0:
b11111111111111111111111111111011 #
b11111111111111111111111111111011 /
b10011100111010101101101001000000110001001100001011010100110111101110011001000000010110100101101001000000010100000101101001101010010000001111000001000000010110100110111001010010010000001101000011010010110011101101000 H
1I
0L
b11111111111111111111111111111011 J
1%
11
#127000
1!
13
1(
14
#130000
0%
01
#135000
03
b0 "
b0 7
0?
b11111111111111111111111111111011 =
b101 A
b0 <
b111 B
1%
11
#137000
0(
04
#140000
0%
01
#145000
b111 <
b10 A
b1110 B
1%
11
#150000
0%
01
#155000
b1 A
b11100 B
1%
11
#160000
0%
01
#165000
0!
b100011 <
b0 A
b111000 B
1%
11
#167000
b11 )
b0 +
#170000
0%
01
#175000
b1110000 B
1%
11
#180000
0%
01
#185000
b11100000 B
1%
11
#190000
0%
01
#195000
b111000000 B
1%
11
#200000
0%
01
#205000
b1110000000 B
1%
11
#210000
0%
01
#215000
b11100000000 B
1%
11
#220000
0%
01
#225000
b111000000000 B
1%
11
#230000
0%
01
#235000
b1110000000000 B
1%
11
#240000
0%
01
#245000
b11100000000000 B
1%
11
#250000
0%
01
#255000
b111000000000000 B
1%
11
#260000
0%
01
#265000
b1110000000000000 B
1%
11
#270000
0%
01
#275000
b11100000000000000 B
1%
11
